Metadata-Version: 2.1
Name: pymodule
Version: 0.2a0
Summary: Python module interface
Home-page: https://github.com/hochshi/pymodule
Author: Shi Hoch
Author-email: pymodule@mailinator.com
License: GPL-3.0
Download-URL: https://github.com/hochshi/pymodule/archive/v0.2-alpha.tar.gz
Keywords: RHEL,module
Platform: UNKNOWN
Classifier: Development Status :: 3 - Alpha
Classifier: Intended Audience :: Developers
Classifier: Topic :: System :: Operating System
Classifier: Programming Language :: Python :: 3
Classifier: Programming Language :: Python :: 3.4
Classifier: Programming Language :: Python :: 3.5
Classifier: Programming Language :: Python :: 3.6
Classifier: Programming Language :: Python :: 3.7
